aworld/__init__.py
aworld/__main__.py
aworld/requirements.txt
aworld/runner.py
aworld/version.py
aworld/version_gen.py
aworld/version_info.py
aworld/agents/__init__.py
aworld/agents/llm_agent.py
aworld/agents/loop_llm_agent.py
aworld/agents/parallel_llm_agent.py
aworld/agents/serial_llm_agent.py
aworld/agents/task_llm_agent.py
aworld/checkpoint/__init__.py
aworld/checkpoint/inmemory.py
aworld/cmd/__init__.py
aworld/cmd/cli.py
aworld/cmd/data_model.py
aworld/cmd/utils/__init__.py
aworld/cmd/utils/agent_executor.py
aworld/cmd/utils/agent_loader.py
aworld/cmd/utils/agent_server.py
aworld/cmd/utils/agent_ui_parser.py
aworld/cmd/utils/trace_summarize.py
aworld/cmd/utils/webui_builder.py
aworld/cmd/web/__init__.py
aworld/cmd/web/api_server.py
aworld/cmd/web/web_server.py
aworld/cmd/web/routers/__init__.py
aworld/cmd/web/routers/chats.py
aworld/cmd/web/routers/sessions.py
aworld/cmd/web/routers/traces.py
aworld/cmd/web/routers/workspaces.py
aworld/cmd/web/utils/__init__.py
aworld/cmd/web/utils/users.py
aworld/cmd/web/webui/dist/aworld_logo.png
aworld/cmd/web/webui/dist/index.html
aworld/cmd/web/webui/dist/trace_ui.html
aworld/cmd/web/webui/dist/assets/App-Dp0UqpP7.css
aworld/cmd/web/webui/dist/assets/App-NnVSuaee.js
aworld/cmd/web/webui/dist/assets/aworld_logo-DnLSZeN8.png
aworld/cmd/web/webui/dist/assets/index-C7nkBYbk.js
aworld/cmd/web/webui/dist/assets/index-CcSzV6ZK.js
aworld/cmd/web/webui/dist/assets/index-DVzAU7Zt.js
aworld/cmd/web/webui/dist/assets/index-I4DyY5Gh.css
aworld/cmd/web/webui/dist/assets/index-TZrNw7dA.css
aworld/cmd/web/webui/dist/assets/index-n9x2b4FL.css
aworld/cmd/web/webui/public/trace_ui.html
aworld/config/__init__.py
aworld/config/agent_loader.py
aworld/config/cl100k_base.tiktoken
aworld/config/conf.py
aworld/config/qwen.tiktoken
aworld/core/__init__.py
aworld/core/common.py
aworld/core/exceptions.py
aworld/core/factory.py
aworld/core/llm_provider.py
aworld/core/memory.py
aworld/core/model_output_parser.py
aworld/core/singleton.py
aworld-0.2.8.dist-info/licenses/LICENSE
aworld-0.2.8.dist-info/METADATA
aworld-0.2.8.dist-info/WHEEL
aworld-0.2.8.dist-info/entry_points.txt
aworld-0.2.8.dist-info/top_level.txt
aworld-0.2.8.dist-info/RECORD
