Metadata-Version: 2.4
Name: aworld
Version: 0.2.8
Summary: Ant Agent Package
Home-page: https://github.com/inclusionAI/AWorld
Author: Ant AI
Author-email: 
License: MIT
Keywords: multi-agent,agent,environment,tool,sandbox
Platform: any
Classifier: Development Status :: 5 - Production/Stable
Classifier: Intended Audience :: Developers
Classifier: Topic :: Software Development :: Build Tools
Classifier: Programming Language :: Python :: 3.10
Classifier: Programming Language :: Python :: 3.11
Classifier: Programming Language :: Python :: 3.12
Requires-Python: >=3.11
License-File: LICENSE
Requires-Dist: pydantic>=2.9.2
Requires-Dist: pyyaml~=6.0.2
Requires-Dist: openai>=1.66.3
Requires-Dist: mcp[cli]~=1.10.1
Requires-Dist: python-dotenv>=1.0.1
Requires-Dist: executing~=2.2.0
Requires-Dist: kubernetes~=32.0.1
Requires-Dist: pyvis>=0.3.2
Requires-Dist: loguru>=0.7.3
Requires-Dist: dataclasses-json>=0.6.7
Requires-Dist: opentelemetry-api~=1.32.1
Requires-Dist: opentelemetry-sdk~=1.32.1
Requires-Dist: opentelemetry-exporter-otlp~=1.32.1
Requires-Dist: tiktoken~=0.9.0
Requires-Dist: fastapi
Requires-Dist: aiohttp~=3.9.5
Requires-Dist: click
Requires-Dist: packaging
Requires-Dist: numpy
Dynamic: author
Dynamic: classifier
Dynamic: description-content-type
Dynamic: home-page
Dynamic: keywords
Dynamic: license
Dynamic: license-file
Dynamic: platform
Dynamic: requires-dist
Dynamic: requires-python
Dynamic: summary
